spatial_link/__init__.py
spatial_link/weekly.py
spatial_link-0.1.0.post3.dist-info/METADATA
spatial_link-0.1.0.post3.dist-info/WHEEL
spatial_link-0.1.0.post3.dist-info/top_level.txt
spatial_link-0.1.0.post3.dist-info/RECORD
