Metadata-Version: 2.4
Name: spatial-link
Version: 0.1.0.post3
Summary: Spatial-Link: A framework for detecting statistically significant linkages from spatio-temporal data.
Author: Maloy Kumar Devnath, Sudip Chakraborty, Vandana P. Janeja
License: iHARP
Project-URL: Homepage, https://github.com/bitsbytes-maker/spatial-link
Project-URL: Repository, https://github.com/bitsbytes-maker/spatial-link
Project-URL: Issues, https://github.com/bitsbytes-maker/spatial-link/issues
Keywords: spatial-link,spatiotemporal,graph,BFS,monte-carlo,linkage-detection,directed-graph,velocity-tensor,geospatial
Classifier: Programming Language :: Python :: 3
Classifier: License :: Other/Proprietary License
Classifier: Operating System :: OS Independent
Classifier: Intended Audience :: Science/Research
Classifier: Topic :: Scientific/Engineering :: Information Analysis
Classifier: Topic :: Scientific/Engineering :: Atmospheric Science
Requires-Python: >=3.9
Requires-Dist: numpy
Requires-Dist: networkx
